ai_safety/__init__.py
ai_safety/ai_safety_manager.py
ai_safety/ai_test_suite.py
ai_safety/constitution_generator/__init__.py
ai_safety/constitution_generator/constitution_generator.py
ai_safety/constitution_generator/constitution_prompt_manager.py
ai_safety/constitution_generator/location_manager.py
ai_safety/content_moderator/__init__.py
ai_safety/content_moderator/content_moderator.py
ai_safety/output_reviser/__init__.py
ai_safety/output_reviser/output_reviser.py
ai_safety-0.1.dist-info/LICENSE
ai_safety-0.1.dist-info/METADATA
ai_safety-0.1.dist-info/WHEEL
ai_safety-0.1.dist-info/top_level.txt
ai_safety-0.1.dist-info/RECORD
