Metadata-Version: 2.1
Name: ai-safety
Version: 0.1
Summary: Open source screening software enhancing safety in large language models
Home-page: https://github.com/zlshinnick/ai-safety.git
Author: Zach Shinnick
Author-email: Zachshinnick03@outlook.com
Classifier: Programming Language :: Python :: 3
Classifier: License :: OSI Approved :: MIT License
License-File: LICENSE
